{"nodes": [{"id": "c_users_poude_documents_capital_website_finlogic_backend_idea_validator_models_py", "label": "models.py", "file_type": "code", "source_file": "C:\\Users\\poude\\Documents\\capital website\\finlogic\\backend\\idea_validator\\models.py", "source_location": "L1"}, {"id": "idea_validator_models_ideavalidatorquota", "label": "IdeaValidatorQuota", "file_type": "code", "source_file": "C:\\Users\\poude\\Documents\\capital website\\finlogic\\backend\\idea_validator\\models.py", "source_location": "L7"}, {"id": "idea_validator_models_meta", "label": "Meta", "file_type": "code", "source_file": "C:\\Users\\poude\\Documents\\capital website\\finlogic\\backend\\idea_validator\\models.py", "source_location": "L24"}, {"id": "idea_validator_models_ideavalidatorquota_str", "label": ".__str__()", "file_type": "code", "source_file": "C:\\Users\\poude\\Documents\\capital website\\finlogic\\backend\\idea_validator\\models.py", "source_location": "L29"}, {"id": "idea_validator_models_get_current_quarter_string", "label": "get_current_quarter_string()", "file_type": "code", "source_file": "C:\\Users\\poude\\Documents\\capital website\\finlogic\\backend\\idea_validator\\models.py", "source_location": "L33"}, {"id": "idea_validator_models_quotaadjustmentlog", "label": "QuotaAdjustmentLog", "file_type": "code", "source_file": "C:\\Users\\poude\\Documents\\capital website\\finlogic\\backend\\idea_validator\\models.py", "source_location": "L38"}, {"id": "idea_validator_models_quotaadjustmentlog_str", "label": ".__str__()", "file_type": "code", "source_file": "C:\\Users\\poude\\Documents\\capital website\\finlogic\\backend\\idea_validator\\models.py", "source_location": "L63"}, {"id": "idea_validator_models_ideavalidationsession", "label": "IdeaValidationSession", "file_type": "code", "source_file": "C:\\Users\\poude\\Documents\\capital website\\finlogic\\backend\\idea_validator\\models.py", "source_location": "L66"}, {"id": "basemodel", "label": "BaseModel", "file_type": "code", "source_file": "", "source_location": ""}, {"id": "idea_validator_models_status", "label": "Status", "file_type": "code", "source_file": "C:\\Users\\poude\\Documents\\capital website\\finlogic\\backend\\idea_validator\\models.py", "source_location": "L71"}, {"id": "idea_validator_models_ideavalidationsession_str", "label": ".__str__()", "file_type": "code", "source_file": "C:\\Users\\poude\\Documents\\capital website\\finlogic\\backend\\idea_validator\\models.py", "source_location": "L110"}, {"id": "idea_validator_models_validationanswer", "label": "ValidationAnswer", "file_type": "code", "source_file": "C:\\Users\\poude\\Documents\\capital website\\finlogic\\backend\\idea_validator\\models.py", "source_location": "L113"}, {"id": "idea_validator_models_validationanswer_str", "label": ".__str__()", "file_type": "code", "source_file": "C:\\Users\\poude\\Documents\\capital website\\finlogic\\backend\\idea_validator\\models.py", "source_location": "L132"}, {"id": "idea_validator_models_validatorprompt", "label": "ValidatorPrompt", "file_type": "code", "source_file": "C:\\Users\\poude\\Documents\\capital website\\finlogic\\backend\\idea_validator\\models.py", "source_location": "L135"}, {"id": "idea_validator_models_validatorprompt_str", "label": ".__str__()", "file_type": "code", "source_file": "C:\\Users\\poude\\Documents\\capital website\\finlogic\\backend\\idea_validator\\models.py", "source_location": "L150"}, {"id": "idea_validator_models_validationsubmissionlog", "label": "ValidationSubmissionLog", "file_type": "code", "source_file": "C:\\Users\\poude\\Documents\\capital website\\finlogic\\backend\\idea_validator\\models.py", "source_location": "L153"}, {"id": "idea_validator_models_validationsubmissionlog_str", "label": ".__str__()", "file_type": "code", "source_file": "C:\\Users\\poude\\Documents\\capital website\\finlogic\\backend\\idea_validator\\models.py", "source_location": "L168"}, {"id": "idea_validator_models_question", "label": "Question", "file_type": "code", "source_file": "C:\\Users\\poude\\Documents\\capital website\\finlogic\\backend\\idea_validator\\models.py", "source_location": "L171"}, {"id": "idea_validator_models_question_str", "label": ".__str__()", "file_type": "code", "source_file": "C:\\Users\\poude\\Documents\\capital website\\finlogic\\backend\\idea_validator\\models.py", "source_location": "L190"}, {"id": "idea_validator_models_option", "label": "Option", "file_type": "code", "source_file": "C:\\Users\\poude\\Documents\\capital website\\finlogic\\backend\\idea_validator\\models.py", "source_location": "L193"}, {"id": "idea_validator_models_option_str", "label": ".__str__()", "file_type": "code", "source_file": "C:\\Users\\poude\\Documents\\capital website\\finlogic\\backend\\idea_validator\\models.py", "source_location": "L206"}, {"id": "idea_validator_models_rationale_8", "label": "Tracks the remaining validations for a user.     Each user receives 1 free vali", "file_type": "rationale", "source_file": "C:\\Users\\poude\\Documents\\capital website\\finlogic\\backend\\idea_validator\\models.py", "source_location": "L8"}, {"id": "idea_validator_models_rationale_39", "label": "Audit log for manual quota adjustments by super-admins.", "file_type": "rationale", "source_file": "C:\\Users\\poude\\Documents\\capital website\\finlogic\\backend\\idea_validator\\models.py", "source_location": "L39"}, {"id": "idea_validator_models_rationale_67", "label": "A single idea validation session.     Isolated from PE deal pipeline.", "file_type": "rationale", "source_file": "C:\\Users\\poude\\Documents\\capital website\\finlogic\\backend\\idea_validator\\models.py", "source_location": "L67"}, {"id": "idea_validator_models_rationale_114", "label": "Answers to the 25 FINLO questions.", "file_type": "rationale", "source_file": "C:\\Users\\poude\\Documents\\capital website\\finlogic\\backend\\idea_validator\\models.py", "source_location": "L114"}, {"id": "idea_validator_models_rationale_136", "label": "Central repository for Validator AI prompts.", "file_type": "rationale", "source_file": "C:\\Users\\poude\\Documents\\capital website\\finlogic\\backend\\idea_validator\\models.py", "source_location": "L136"}, {"id": "idea_validator_models_rationale_154", "label": "Audit log for validation submissions.", "file_type": "rationale", "source_file": "C:\\Users\\poude\\Documents\\capital website\\finlogic\\backend\\idea_validator\\models.py", "source_location": "L154"}, {"id": "idea_validator_models_rationale_172", "label": "Dynamic validator questions.", "file_type": "rationale", "source_file": "C:\\Users\\poude\\Documents\\capital website\\finlogic\\backend\\idea_validator\\models.py", "source_location": "L172"}, {"id": "idea_validator_models_rationale_194", "label": "Options for a specific question.", "file_type": "rationale", "source_file": "C:\\Users\\poude\\Documents\\capital website\\finlogic\\backend\\idea_validator\\models.py", "source_location": "L194"}], "edges": [{"source": "c_users_poude_documents_capital_website_finlogic_backend_idea_validator_models_py", "target": "uuid", "relation": "imports", "confidence": "EXTRACTED", "source_file": "C:\\Users\\poude\\Documents\\capital website\\finlogic\\backend\\idea_validator\\models.py", "source_location": "L1", "weight": 1.0}, {"source": "c_users_poude_documents_capital_website_finlogic_backend_idea_validator_models_py", "target": "django_db", "relation": "imports_from", "confidence": "EXTRACTED", "source_file": "C:\\Users\\poude\\Documents\\capital website\\finlogic\\backend\\idea_validator\\models.py", "source_location": "L2", "weight": 1.0}, {"source": "c_users_poude_documents_capital_website_finlogic_backend_idea_validator_models_py", "target": "django_conf", "relation": "imports_from", "confidence": "EXTRACTED", "source_file": "C:\\Users\\poude\\Documents\\capital website\\finlogic\\backend\\idea_validator\\models.py", "source_location": "L3", "weight": 1.0}, {"source": "c_users_poude_documents_capital_website_finlogic_backend_idea_validator_models_py", "target": "core_models", "relation": "imports_from", "confidence": "EXTRACTED", "source_file": "C:\\Users\\poude\\Documents\\capital website\\finlogic\\backend\\idea_validator\\models.py", "source_location": "L4", "weight": 1.0}, {"source": "c_users_poude_documents_capital_website_finlogic_backend_idea_validator_models_py", "target": "django_utils", "relation": "imports_from", "confidence": "EXTRACTED", "source_file": "C:\\Users\\poude\\Documents\\capital website\\finlogic\\backend\\idea_validator\\models.py", "source_location": "L5", "weight": 1.0}, {"source": "c_users_poude_documents_capital_website_finlogic_backend_idea_validator_models_py", "target": "idea_validator_models_ideavalidatorquota", "relation": "contains", "confidence": "EXTRACTED", "source_file": "C:\\Users\\poude\\Documents\\capital website\\finlogic\\backend\\idea_validator\\models.py", "source_location": "L7", "weight": 1.0}, {"source": "c_users_poude_documents_capital_website_finlogic_backend_idea_validator_models_py", "target": "idea_validator_models_meta", "relation": "contains", "confidence": "EXTRACTED", "source_file": "C:\\Users\\poude\\Documents\\capital website\\finlogic\\backend\\idea_validator\\models.py", "source_location": "L24", "weight": 1.0}, {"source": "idea_validator_models_ideavalidatorquota", "target": "idea_validator_models_ideavalidatorquota_str", "relation": "method", "confidence": "EXTRACTED", "source_file": "C:\\Users\\poude\\Documents\\capital website\\finlogic\\backend\\idea_validator\\models.py", "source_location": "L29", "weight": 1.0}, {"source": "c_users_poude_documents_capital_website_finlogic_backend_idea_validator_models_py", "target": "idea_validator_models_get_current_quarter_string", "relation": "contains", "confidence": "EXTRACTED", "source_file": "C:\\Users\\poude\\Documents\\capital website\\finlogic\\backend\\idea_validator\\models.py", "source_location": "L33", "weight": 1.0}, {"source": "c_users_poude_documents_capital_website_finlogic_backend_idea_validator_models_py", "target": "idea_validator_models_quotaadjustmentlog", "relation": "contains", "confidence": "EXTRACTED", "source_file": "C:\\Users\\poude\\Documents\\capital website\\finlogic\\backend\\idea_validator\\models.py", "source_location": "L38", "weight": 1.0}, {"source": "c_users_poude_documents_capital_website_finlogic_backend_idea_validator_models_py", "target": "idea_validator_models_meta", "relation": "contains", "confidence": "EXTRACTED", "source_file": "C:\\Users\\poude\\Documents\\capital website\\finlogic\\backend\\idea_validator\\models.py", "source_location": "L59", "weight": 1.0}, {"source": "idea_validator_models_quotaadjustmentlog", "target": "idea_validator_models_quotaadjustmentlog_str", "relation": "method", "confidence": "EXTRACTED", "source_file": "C:\\Users\\poude\\Documents\\capital website\\finlogic\\backend\\idea_validator\\models.py", "source_location": "L63", "weight": 1.0}, {"source": "c_users_poude_documents_capital_website_finlogic_backend_idea_validator_models_py", "target": "idea_validator_models_ideavalidationsession", "relation": "contains", "confidence": "EXTRACTED", "source_file": "C:\\Users\\poude\\Documents\\capital website\\finlogic\\backend\\idea_validator\\models.py", "source_location": "L66", "weight": 1.0}, {"source": "idea_validator_models_ideavalidationsession", "target": "basemodel", "relation": "inherits", "confidence": "EXTRACTED", "source_file": "C:\\Users\\poude\\Documents\\capital website\\finlogic\\backend\\idea_validator\\models.py", "source_location": "L66", "weight": 1.0}, {"source": "c_users_poude_documents_capital_website_finlogic_backend_idea_validator_models_py", "target": "idea_validator_models_status", "relation": "contains", "confidence": "EXTRACTED", "source_file": "C:\\Users\\poude\\Documents\\capital website\\finlogic\\backend\\idea_validator\\models.py", "source_location": "L71", "weight": 1.0}, {"source": "c_users_poude_documents_capital_website_finlogic_backend_idea_validator_models_py", "target": "idea_validator_models_meta", "relation": "contains", "confidence": "EXTRACTED", "source_file": "C:\\Users\\poude\\Documents\\capital website\\finlogic\\backend\\idea_validator\\models.py", "source_location": "L105", "weight": 1.0}, {"source": "idea_validator_models_ideavalidationsession", "target": "idea_validator_models_ideavalidationsession_str", "relation": "method", "confidence": "EXTRACTED", "source_file": "C:\\Users\\poude\\Documents\\capital website\\finlogic\\backend\\idea_validator\\models.py", "source_location": "L110", "weight": 1.0}, {"source": "c_users_poude_documents_capital_website_finlogic_backend_idea_validator_models_py", "target": "idea_validator_models_validationanswer", "relation": "contains", "confidence": "EXTRACTED", "source_file": "C:\\Users\\poude\\Documents\\capital website\\finlogic\\backend\\idea_validator\\models.py", "source_location": "L113", "weight": 1.0}, {"source": "c_users_poude_documents_capital_website_finlogic_backend_idea_validator_models_py", "target": "idea_validator_models_meta", "relation": "contains", "confidence": "EXTRACTED", "source_file": "C:\\Users\\poude\\Documents\\capital website\\finlogic\\backend\\idea_validator\\models.py", "source_location": "L127", "weight": 1.0}, {"source": "idea_validator_models_validationanswer", "target": "idea_validator_models_validationanswer_str", "relation": "method", "confidence": "EXTRACTED", "source_file": "C:\\Users\\poude\\Documents\\capital website\\finlogic\\backend\\idea_validator\\models.py", "source_location": "L132", "weight": 1.0}, {"source": "c_users_poude_documents_capital_website_finlogic_backend_idea_validator_models_py", "target": "idea_validator_models_validatorprompt", "relation": "contains", "confidence": "EXTRACTED", "source_file": "C:\\Users\\poude\\Documents\\capital website\\finlogic\\backend\\idea_validator\\models.py", "source_location": "L135", "weight": 1.0}, {"source": "c_users_poude_documents_capital_website_finlogic_backend_idea_validator_models_py", "target": "idea_validator_models_meta", "relation": "contains", "confidence": "EXTRACTED", "source_file": "C:\\Users\\poude\\Documents\\capital website\\finlogic\\backend\\idea_validator\\models.py", "source_location": "L145", "weight": 1.0}, {"source": "idea_validator_models_validatorprompt", "target": "idea_validator_models_validatorprompt_str", "relation": "method", "confidence": "EXTRACTED", "source_file": "C:\\Users\\poude\\Documents\\capital website\\finlogic\\backend\\idea_validator\\models.py", "source_location": "L150", "weight": 1.0}, {"source": "c_users_poude_documents_capital_website_finlogic_backend_idea_validator_models_py", "target": "idea_validator_models_validationsubmissionlog", "relation": "contains", "confidence": "EXTRACTED", "source_file": "C:\\Users\\poude\\Documents\\capital website\\finlogic\\backend\\idea_validator\\models.py", "source_location": "L153", "weight": 1.0}, {"source": "c_users_poude_documents_capital_website_finlogic_backend_idea_validator_models_py", "target": "idea_validator_models_meta", "relation": "contains", "confidence": "EXTRACTED", "source_file": "C:\\Users\\poude\\Documents\\capital website\\finlogic\\backend\\idea_validator\\models.py", "source_location": "L165", "weight": 1.0}, {"source": "idea_validator_models_validationsubmissionlog", "target": "idea_validator_models_validationsubmissionlog_str", "relation": "method", "confidence": "EXTRACTED", "source_file": "C:\\Users\\poude\\Documents\\capital website\\finlogic\\backend\\idea_validator\\models.py", "source_location": "L168", "weight": 1.0}, {"source": "c_users_poude_documents_capital_website_finlogic_backend_idea_validator_models_py", "target": "idea_validator_models_question", "relation": "contains", "confidence": "EXTRACTED", "source_file": "C:\\Users\\poude\\Documents\\capital website\\finlogic\\backend\\idea_validator\\models.py", "source_location": "L171", "weight": 1.0}, {"source": "c_users_poude_documents_capital_website_finlogic_backend_idea_validator_models_py", "target": "idea_validator_models_meta", "relation": "contains", "confidence": "EXTRACTED", "source_file": "C:\\Users\\poude\\Documents\\capital website\\finlogic\\backend\\idea_validator\\models.py", "source_location": "L186", "weight": 1.0}, {"source": "idea_validator_models_question", "target": "idea_validator_models_question_str", "relation": "method", "confidence": "EXTRACTED", "source_file": "C:\\Users\\poude\\Documents\\capital website\\finlogic\\backend\\idea_validator\\models.py", "source_location": "L190", "weight": 1.0}, {"source": "c_users_poude_documents_capital_website_finlogic_backend_idea_validator_models_py", "target": "idea_validator_models_option", "relation": "contains", "confidence": "EXTRACTED", "source_file": "C:\\Users\\poude\\Documents\\capital website\\finlogic\\backend\\idea_validator\\models.py", "source_location": "L193", "weight": 1.0}, {"source": "c_users_poude_documents_capital_website_finlogic_backend_idea_validator_models_py", "target": "idea_validator_models_meta", "relation": "contains", "confidence": "EXTRACTED", "source_file": "C:\\Users\\poude\\Documents\\capital website\\finlogic\\backend\\idea_validator\\models.py", "source_location": "L202", "weight": 1.0}, {"source": "idea_validator_models_option", "target": "idea_validator_models_option_str", "relation": "method", "confidence": "EXTRACTED", "source_file": "C:\\Users\\poude\\Documents\\capital website\\finlogic\\backend\\idea_validator\\models.py", "source_location": "L206", "weight": 1.0}, {"source": "idea_validator_models_rationale_8", "target": "idea_validator_models_ideavalidatorquota", "relation": "rationale_for", "confidence": "EXTRACTED", "source_file": "C:\\Users\\poude\\Documents\\capital website\\finlogic\\backend\\idea_validator\\models.py", "source_location": "L8", "weight": 1.0}, {"source": "idea_validator_models_rationale_39", "target": "idea_validator_models_quotaadjustmentlog", "relation": "rationale_for", "confidence": "EXTRACTED", "source_file": "C:\\Users\\poude\\Documents\\capital website\\finlogic\\backend\\idea_validator\\models.py", "source_location": "L39", "weight": 1.0}, {"source": "idea_validator_models_rationale_67", "target": "idea_validator_models_ideavalidationsession", "relation": "rationale_for", "confidence": "EXTRACTED", "source_file": "C:\\Users\\poude\\Documents\\capital website\\finlogic\\backend\\idea_validator\\models.py", "source_location": "L67", "weight": 1.0}, {"source": "idea_validator_models_rationale_114", "target": "idea_validator_models_validationanswer", "relation": "rationale_for", "confidence": "EXTRACTED", "source_file": "C:\\Users\\poude\\Documents\\capital website\\finlogic\\backend\\idea_validator\\models.py", "source_location": "L114", "weight": 1.0}, {"source": "idea_validator_models_rationale_136", "target": "idea_validator_models_validatorprompt", "relation": "rationale_for", "confidence": "EXTRACTED", "source_file": "C:\\Users\\poude\\Documents\\capital website\\finlogic\\backend\\idea_validator\\models.py", "source_location": "L136", "weight": 1.0}, {"source": "idea_validator_models_rationale_154", "target": "idea_validator_models_validationsubmissionlog", "relation": "rationale_for", "confidence": "EXTRACTED", "source_file": "C:\\Users\\poude\\Documents\\capital website\\finlogic\\backend\\idea_validator\\models.py", "source_location": "L154", "weight": 1.0}, {"source": "idea_validator_models_rationale_172", "target": "idea_validator_models_question", "relation": "rationale_for", "confidence": "EXTRACTED", "source_file": "C:\\Users\\poude\\Documents\\capital website\\finlogic\\backend\\idea_validator\\models.py", "source_location": "L172", "weight": 1.0}, {"source": "idea_validator_models_rationale_194", "target": "idea_validator_models_option", "relation": "rationale_for", "confidence": "EXTRACTED", "source_file": "C:\\Users\\poude\\Documents\\capital website\\finlogic\\backend\\idea_validator\\models.py", "source_location": "L194", "weight": 1.0}], "raw_calls": [{"caller_nid": "idea_validator_models_get_current_quarter_string", "callee": "now", "is_member_call": true, "source_file": "C:\\Users\\poude\\Documents\\capital website\\finlogic\\backend\\idea_validator\\models.py", "source_location": "L34"}]}