{"nodes": [{"id": "c_users_poude_documents_capital_website_finlogic_frontend_src_app_gp_gp_fund_admin_documents_page_jsx", "label": "page.jsx", "file_type": "code", "source_file": "C:\\Users\\poude\\Documents\\capital website\\finlogic\\frontend\\src\\app\\(gp)\\gp\\fund-admin\\documents\\page.jsx", "source_location": "L1"}, {"id": "documents_page_gpfunddocumentspage", "label": "GPFundDocumentsPage()", "file_type": "code", "source_file": "C:\\Users\\poude\\Documents\\capital website\\finlogic\\frontend\\src\\app\\(gp)\\gp\\fund-admin\\documents\\page.jsx", "source_location": "L37"}], "edges": [{"source": "c_users_poude_documents_capital_website_finlogic_frontend_src_app_gp_gp_fund_admin_documents_page_jsx", "target": "react", "relation": "imports_from", "confidence": "EXTRACTED", "source_file": "C:\\Users\\poude\\Documents\\capital website\\finlogic\\frontend\\src\\app\\(gp)\\gp\\fund-admin\\documents\\page.jsx", "source_location": "L3", "weight": 1.0}, {"source": "c_users_poude_documents_capital_website_finlogic_frontend_src_app_gp_gp_fund_admin_documents_page_jsx", "target": "lucide_react", "relation": "imports_from", "confidence": "EXTRACTED", "source_file": "C:\\Users\\poude\\Documents\\capital website\\finlogic\\frontend\\src\\app\\(gp)\\gp\\fund-admin\\documents\\page.jsx", "source_location": "L4", "weight": 1.0}, {"source": "c_users_poude_documents_capital_website_finlogic_frontend_src_app_gp_gp_fund_admin_documents_page_jsx", "target": "c_users_poude_documents_capital_website_services_api", "relation": "imports_from", "confidence": "EXTRACTED", "source_file": "C:\\Users\\poude\\Documents\\capital website\\finlogic\\frontend\\src\\app\\(gp)\\gp\\fund-admin\\documents\\page.jsx", "source_location": "L21", "weight": 1.0}, {"source": "c_users_poude_documents_capital_website_finlogic_frontend_src_app_gp_gp_fund_admin_documents_page_jsx", "target": "sonner", "relation": "imports_from", "confidence": "EXTRACTED", "source_file": "C:\\Users\\poude\\Documents\\capital website\\finlogic\\frontend\\src\\app\\(gp)\\gp\\fund-admin\\documents\\page.jsx", "source_location": "L22", "weight": 1.0}, {"source": "c_users_poude_documents_capital_website_finlogic_frontend_src_app_gp_gp_fund_admin_documents_page_jsx", "target": "c_users_poude_documents_capital_website_components_portal_fileuploader", "relation": "imports_from", "confidence": "EXTRACTED", "source_file": "C:\\Users\\poude\\Documents\\capital website\\finlogic\\frontend\\src\\app\\(gp)\\gp\\fund-admin\\documents\\page.jsx", "source_location": "L23", "weight": 1.0}, {"source": "c_users_poude_documents_capital_website_finlogic_frontend_src_app_gp_gp_fund_admin_documents_page_jsx", "target": "documents_page_gpfunddocumentspage", "relation": "contains", "confidence": "EXTRACTED", "source_file": "C:\\Users\\poude\\Documents\\capital website\\finlogic\\frontend\\src\\app\\(gp)\\gp\\fund-admin\\documents\\page.jsx", "source_location": "L37", "weight": 1.0}], "raw_calls": [{"caller_nid": "documents_page_gpfunddocumentspage", "callee": "useState", "is_member_call": false, "source_file": "C:\\Users\\poude\\Documents\\capital website\\finlogic\\frontend\\src\\app\\(gp)\\gp\\fund-admin\\documents\\page.jsx", "source_location": "L38"}, {"caller_nid": "documents_page_gpfunddocumentspage", "callee": "useState", "is_member_call": false, "source_file": "C:\\Users\\poude\\Documents\\capital website\\finlogic\\frontend\\src\\app\\(gp)\\gp\\fund-admin\\documents\\page.jsx", "source_location": "L39"}, {"caller_nid": "documents_page_gpfunddocumentspage", "callee": "useState", "is_member_call": false, "source_file": "C:\\Users\\poude\\Documents\\capital website\\finlogic\\frontend\\src\\app\\(gp)\\gp\\fund-admin\\documents\\page.jsx", "source_location": "L40"}, {"caller_nid": "documents_page_gpfunddocumentspage", "callee": "useState", "is_member_call": false, "source_file": "C:\\Users\\poude\\Documents\\capital website\\finlogic\\frontend\\src\\app\\(gp)\\gp\\fund-admin\\documents\\page.jsx", "source_location": "L41"}, {"caller_nid": "documents_page_gpfunddocumentspage", "callee": "useState", "is_member_call": false, "source_file": "C:\\Users\\poude\\Documents\\capital website\\finlogic\\frontend\\src\\app\\(gp)\\gp\\fund-admin\\documents\\page.jsx", "source_location": "L42"}, {"caller_nid": "documents_page_gpfunddocumentspage", "callee": "useState", "is_member_call": false, "source_file": "C:\\Users\\poude\\Documents\\capital website\\finlogic\\frontend\\src\\app\\(gp)\\gp\\fund-admin\\documents\\page.jsx", "source_location": "L45"}, {"caller_nid": "documents_page_gpfunddocumentspage", "callee": "useEffect", "is_member_call": false, "source_file": "C:\\Users\\poude\\Documents\\capital website\\finlogic\\frontend\\src\\app\\(gp)\\gp\\fund-admin\\documents\\page.jsx", "source_location": "L55"}, {"caller_nid": "documents_page_gpfunddocumentspage", "callee": "useEffect", "is_member_call": false, "source_file": "C:\\Users\\poude\\Documents\\capital website\\finlogic\\frontend\\src\\app\\(gp)\\gp\\fund-admin\\documents\\page.jsx", "source_location": "L59"}, {"caller_nid": "documents_page_gpfunddocumentspage", "callee": "map", "is_member_call": true, "source_file": "C:\\Users\\poude\\Documents\\capital website\\finlogic\\frontend\\src\\app\\(gp)\\gp\\fund-admin\\documents\\page.jsx", "source_location": "L161"}, {"caller_nid": "documents_page_gpfunddocumentspage", "callee": "filter", "is_member_call": true, "source_file": "C:\\Users\\poude\\Documents\\capital website\\finlogic\\frontend\\src\\app\\(gp)\\gp\\fund-admin\\documents\\page.jsx", "source_location": "L190"}, {"caller_nid": "documents_page_gpfunddocumentspage", "callee": "filter", "is_member_call": true, "source_file": "C:\\Users\\poude\\Documents\\capital website\\finlogic\\frontend\\src\\app\\(gp)\\gp\\fund-admin\\documents\\page.jsx", "source_location": "L195"}, {"caller_nid": "documents_page_gpfunddocumentspage", "callee": "map", "is_member_call": true, "source_file": "C:\\Users\\poude\\Documents\\capital website\\finlogic\\frontend\\src\\app\\(gp)\\gp\\fund-admin\\documents\\page.jsx", "source_location": "L232"}, {"caller_nid": "documents_page_gpfunddocumentspage", "callee": "map", "is_member_call": true, "source_file": "C:\\Users\\poude\\Documents\\capital website\\finlogic\\frontend\\src\\app\\(gp)\\gp\\fund-admin\\documents\\page.jsx", "source_location": "L324"}]}