{"nodes": [{"id": "c_users_poude_documents_capital_website_finlogic_backend_deals_serializers_fund_py", "label": "fund.py", "file_type": "code", "source_file": "C:\\Users\\poude\\Documents\\capital website\\finlogic\\backend\\deals\\serializers\\fund.py", "source_location": "L1"}, {"id": "serializers_fund_userminiserializer", "label": "UserMiniSerializer", "file_type": "code", "source_file": "C:\\Users\\poude\\Documents\\capital website\\finlogic\\backend\\deals\\serializers\\fund.py", "source_location": "L75"}, {"id": "serializers_fund_meta", "label": "Meta", "file_type": "code", "source_file": "C:\\Users\\poude\\Documents\\capital website\\finlogic\\backend\\deals\\serializers\\fund.py", "source_location": "L76"}, {"id": "serializers_fund_immutableauditeventserializer", "label": "ImmutableAuditEventSerializer", "file_type": "code", "source_file": "C:\\Users\\poude\\Documents\\capital website\\finlogic\\backend\\deals\\serializers\\fund.py", "source_location": "L87"}, {"id": "serializers_fund_fundserializer", "label": "FundSerializer", "file_type": "code", "source_file": "C:\\Users\\poude\\Documents\\capital website\\finlogic\\backend\\deals\\serializers\\fund.py", "source_location": "L108"}, {"id": "serializers_fund_fundserializer_get_performance", "label": ".get_performance()", "file_type": "code", "source_file": "C:\\Users\\poude\\Documents\\capital website\\finlogic\\backend\\deals\\serializers\\fund.py", "source_location": "L116"}, {"id": "serializers_fund_lpprofileserializer", "label": "LPProfileSerializer", "file_type": "code", "source_file": "C:\\Users\\poude\\Documents\\capital website\\finlogic\\backend\\deals\\serializers\\fund.py", "source_location": "L141"}, {"id": "serializers_fund_lpkycdocumentserializer", "label": "LPKYCDocumentSerializer", "file_type": "code", "source_file": "C:\\Users\\poude\\Documents\\capital website\\finlogic\\backend\\deals\\serializers\\fund.py", "source_location": "L156"}, {"id": "serializers_fund_entrepreneurkybdocumentserializer", "label": "EntrepreneurKYBDocumentSerializer", "file_type": "code", "source_file": "C:\\Users\\poude\\Documents\\capital website\\finlogic\\backend\\deals\\serializers\\fund.py", "source_location": "L169"}, {"id": "serializers_fund_lpfundcommitmentserializer", "label": "LPFundCommitmentSerializer", "file_type": "code", "source_file": "C:\\Users\\poude\\Documents\\capital website\\finlogic\\backend\\deals\\serializers\\fund.py", "source_location": "L186"}, {"id": "serializers_fund_peinvestmentserializer", "label": "PEInvestmentSerializer", "file_type": "code", "source_file": "C:\\Users\\poude\\Documents\\capital website\\finlogic\\backend\\deals\\serializers\\fund.py", "source_location": "L218"}, {"id": "serializers_fund_capitalcallserializer", "label": "CapitalCallSerializer", "file_type": "code", "source_file": "C:\\Users\\poude\\Documents\\capital website\\finlogic\\backend\\deals\\serializers\\fund.py", "source_location": "L247"}, {"id": "serializers_fund_capitalcallserializer_get_lp_profile_detail", "label": ".get_lp_profile_detail()", "file_type": "code", "source_file": "C:\\Users\\poude\\Documents\\capital website\\finlogic\\backend\\deals\\serializers\\fund.py", "source_location": "L271"}, {"id": "serializers_fund_distributionserializer", "label": "DistributionSerializer", "file_type": "code", "source_file": "C:\\Users\\poude\\Documents\\capital website\\finlogic\\backend\\deals\\serializers\\fund.py", "source_location": "L287"}, {"id": "serializers_fund_lpdashboardfundserializer", "label": "LPDashboardFundSerializer", "file_type": "code", "source_file": "C:\\Users\\poude\\Documents\\capital website\\finlogic\\backend\\deals\\serializers\\fund.py", "source_location": "L309"}, {"id": "serializers_fund_lpdashboardfundserializer_get_my_commitment", "label": ".get_my_commitment()", "file_type": "code", "source_file": "C:\\Users\\poude\\Documents\\capital website\\finlogic\\backend\\deals\\serializers\\fund.py", "source_location": "L326"}, {"id": "serializers_fund_lpdashboardfundserializer_get_approved_deals_count", "label": ".get_approved_deals_count()", "file_type": "code", "source_file": "C:\\Users\\poude\\Documents\\capital website\\finlogic\\backend\\deals\\serializers\\fund.py", "source_location": "L337"}, {"id": "serializers_fund_lpdashboardfundserializer_get_total_documents_count", "label": ".get_total_documents_count()", "file_type": "code", "source_file": "C:\\Users\\poude\\Documents\\capital website\\finlogic\\backend\\deals\\serializers\\fund.py", "source_location": "L342"}, {"id": "serializers_fund_lpdashboardfundserializer_get_pending_action_count", "label": ".get_pending_action_count()", "file_type": "code", "source_file": "C:\\Users\\poude\\Documents\\capital website\\finlogic\\backend\\deals\\serializers\\fund.py", "source_location": "L345"}, {"id": "serializers_fund_managementfeeaccrualserializer", "label": "ManagementFeeAccrualSerializer", "file_type": "code", "source_file": "C:\\Users\\poude\\Documents\\capital website\\finlogic\\backend\\deals\\serializers\\fund.py", "source_location": "L363"}, {"id": "serializers_fund_gpinvestordashboardserializer", "label": "GPInvestorDashboardSerializer", "file_type": "code", "source_file": "C:\\Users\\poude\\Documents\\capital website\\finlogic\\backend\\deals\\serializers\\fund.py", "source_location": "L374"}, {"id": "serializers_fund_lpportfolioserializer", "label": "LPPortfolioSerializer", "file_type": "code", "source_file": "C:\\Users\\poude\\Documents\\capital website\\finlogic\\backend\\deals\\serializers\\fund.py", "source_location": "L388"}, {"id": "serializers_fund_lpportfolioserializer_get_anonymized_name", "label": ".get_anonymized_name()", "file_type": "code", "source_file": "C:\\Users\\poude\\Documents\\capital website\\finlogic\\backend\\deals\\serializers\\fund.py", "source_location": "L400"}, {"id": "serializers_fund_lpsupportrequestserializer", "label": "LPSupportRequestSerializer", "file_type": "code", "source_file": "C:\\Users\\poude\\Documents\\capital website\\finlogic\\backend\\deals\\serializers\\fund.py", "source_location": "L410"}, {"id": "serializers_fund_rationale_1", "label": "deals/serializers.py DRF serializers for all PE Deals models.", "file_type": "rationale", "source_file": "C:\\Users\\poude\\Documents\\capital website\\finlogic\\backend\\deals\\serializers\\fund.py", "source_location": "L1"}, {"id": "serializers_fund_rationale_310", "label": "Fund data enriched with the LP's commitment summary.", "file_type": "rationale", "source_file": "C:\\Users\\poude\\Documents\\capital website\\finlogic\\backend\\deals\\serializers\\fund.py", "source_location": "L310"}, {"id": "serializers_fund_rationale_375", "label": "Read-only summary for GP Investor portal.", "file_type": "rationale", "source_file": "C:\\Users\\poude\\Documents\\capital website\\finlogic\\backend\\deals\\serializers\\fund.py", "source_location": "L375"}, {"id": "serializers_fund_rationale_389", "label": "Anonymized project data for LP portfolio view.", "file_type": "rationale", "source_file": "C:\\Users\\poude\\Documents\\capital website\\finlogic\\backend\\deals\\serializers\\fund.py", "source_location": "L389"}], "edges": [{"source": "c_users_poude_documents_capital_website_finlogic_backend_deals_serializers_fund_py", "target": "django_conf", "relation": "imports_from", "confidence": "EXTRACTED", "source_file": "C:\\Users\\poude\\Documents\\capital website\\finlogic\\backend\\deals\\serializers\\fund.py", "source_location": "L5", "weight": 1.0}, {"source": "c_users_poude_documents_capital_website_finlogic_backend_deals_serializers_fund_py", "target": "django_contrib_auth", "relation": "imports_from", "confidence": "EXTRACTED", "source_file": "C:\\Users\\poude\\Documents\\capital website\\finlogic\\backend\\deals\\serializers\\fund.py", "source_location": "L6", "weight": 1.0}, {"source": "c_users_poude_documents_capital_website_finlogic_backend_deals_serializers_fund_py", "target": "rest_framework", "relation": "imports_from", "confidence": "EXTRACTED", "source_file": "C:\\Users\\poude\\Documents\\capital website\\finlogic\\backend\\deals\\serializers\\fund.py", "source_location": "L7", "weight": 1.0}, {"source": "c_users_poude_documents_capital_website_finlogic_backend_deals_serializers_fund_py", "target": "deals_models", "relation": "imports_from", "confidence": "EXTRACTED", "source_file": "C:\\Users\\poude\\Documents\\capital website\\finlogic\\backend\\deals\\serializers\\fund.py", "source_location": "L9", "weight": 1.0}, {"source": "c_users_poude_documents_capital_website_finlogic_backend_deals_serializers_fund_py", "target": "serializers_fund_userminiserializer", "relation": "contains", "confidence": "EXTRACTED", "source_file": "C:\\Users\\poude\\Documents\\capital website\\finlogic\\backend\\deals\\serializers\\fund.py", "source_location": "L75", "weight": 1.0}, {"source": "c_users_poude_documents_capital_website_finlogic_backend_deals_serializers_fund_py", "target": "serializers_fund_meta", "relation": "contains", "confidence": "EXTRACTED", "source_file": "C:\\Users\\poude\\Documents\\capital website\\finlogic\\backend\\deals\\serializers\\fund.py", "source_location": "L76", "weight": 1.0}, {"source": "c_users_poude_documents_capital_website_finlogic_backend_deals_serializers_fund_py", "target": "serializers_fund_immutableauditeventserializer", "relation": "contains", "confidence": "EXTRACTED", "source_file": "C:\\Users\\poude\\Documents\\capital website\\finlogic\\backend\\deals\\serializers\\fund.py", "source_location": "L87", "weight": 1.0}, {"source": "c_users_poude_documents_capital_website_finlogic_backend_deals_serializers_fund_py", "target": "serializers_fund_meta", "relation": "contains", "confidence": "EXTRACTED", "source_file": "C:\\Users\\poude\\Documents\\capital website\\finlogic\\backend\\deals\\serializers\\fund.py", "source_location": "L93", "weight": 1.0}, {"source": "c_users_poude_documents_capital_website_finlogic_backend_deals_serializers_fund_py", "target": "serializers_fund_fundserializer", "relation": "contains", "confidence": "EXTRACTED", "source_file": "C:\\Users\\poude\\Documents\\capital website\\finlogic\\backend\\deals\\serializers\\fund.py", "source_location": "L108", "weight": 1.0}, {"source": "serializers_fund_fundserializer", "target": "serializers_fund_fundserializer_get_performance", "relation": "method", "confidence": "EXTRACTED", "source_file": "C:\\Users\\poude\\Documents\\capital website\\finlogic\\backend\\deals\\serializers\\fund.py", "source_location": "L116", "weight": 1.0}, {"source": "c_users_poude_documents_capital_website_finlogic_backend_deals_serializers_fund_py", "target": "serializers_fund_meta", "relation": "contains", "confidence": "EXTRACTED", "source_file": "C:\\Users\\poude\\Documents\\capital website\\finlogic\\backend\\deals\\serializers\\fund.py", "source_location": "L120", "weight": 1.0}, {"source": "c_users_poude_documents_capital_website_finlogic_backend_deals_serializers_fund_py", "target": "serializers_fund_lpprofileserializer", "relation": "contains", "confidence": "EXTRACTED", "source_file": "C:\\Users\\poude\\Documents\\capital website\\finlogic\\backend\\deals\\serializers\\fund.py", "source_location": "L141", "weight": 1.0}, {"source": "c_users_poude_documents_capital_website_finlogic_backend_deals_serializers_fund_py", "target": "serializers_fund_meta", "relation": "contains", "confidence": "EXTRACTED", "source_file": "C:\\Users\\poude\\Documents\\capital website\\finlogic\\backend\\deals\\serializers\\fund.py", "source_location": "L144", "weight": 1.0}, {"source": "c_users_poude_documents_capital_website_finlogic_backend_deals_serializers_fund_py", "target": "serializers_fund_lpkycdocumentserializer", "relation": "contains", "confidence": "EXTRACTED", "source_file": "C:\\Users\\poude\\Documents\\capital website\\finlogic\\backend\\deals\\serializers\\fund.py", "source_location": "L156", "weight": 1.0}, {"source": "c_users_poude_documents_capital_website_finlogic_backend_deals_serializers_fund_py", "target": "serializers_fund_meta", "relation": "contains", "confidence": "EXTRACTED", "source_file": "C:\\Users\\poude\\Documents\\capital website\\finlogic\\backend\\deals\\serializers\\fund.py", "source_location": "L159", "weight": 1.0}, {"source": "c_users_poude_documents_capital_website_finlogic_backend_deals_serializers_fund_py", "target": "serializers_fund_entrepreneurkybdocumentserializer", "relation": "contains", "confidence": "EXTRACTED", "source_file": "C:\\Users\\poude\\Documents\\capital website\\finlogic\\backend\\deals\\serializers\\fund.py", "source_location": "L169", "weight": 1.0}, {"source": "c_users_poude_documents_capital_website_finlogic_backend_deals_serializers_fund_py", "target": "serializers_fund_meta", "relation": "contains", "confidence": "EXTRACTED", "source_file": "C:\\Users\\poude\\Documents\\capital website\\finlogic\\backend\\deals\\serializers\\fund.py", "source_location": "L172", "weight": 1.0}, {"source": "c_users_poude_documents_capital_website_finlogic_backend_deals_serializers_fund_py", "target": "serializers_fund_lpfundcommitmentserializer", "relation": "contains", "confidence": "EXTRACTED", "source_file": "C:\\Users\\poude\\Documents\\capital website\\finlogic\\backend\\deals\\serializers\\fund.py", "source_location": "L186", "weight": 1.0}, {"source": "c_users_poude_documents_capital_website_finlogic_backend_deals_serializers_fund_py", "target": "serializers_fund_meta", "relation": "contains", "confidence": "EXTRACTED", "source_file": "C:\\Users\\poude\\Documents\\capital website\\finlogic\\backend\\deals\\serializers\\fund.py", "source_location": "L194", "weight": 1.0}, {"source": "c_users_poude_documents_capital_website_finlogic_backend_deals_serializers_fund_py", "target": "serializers_fund_peinvestmentserializer", "relation": "contains", "confidence": "EXTRACTED", "source_file": "C:\\Users\\poude\\Documents\\capital website\\finlogic\\backend\\deals\\serializers\\fund.py", "source_location": "L218", "weight": 1.0}, {"source": "c_users_poude_documents_capital_website_finlogic_backend_deals_serializers_fund_py", "target": "serializers_fund_meta", "relation": "contains", "confidence": "EXTRACTED", "source_file": "C:\\Users\\poude\\Documents\\capital website\\finlogic\\backend\\deals\\serializers\\fund.py", "source_location": "L226", "weight": 1.0}, {"source": "c_users_poude_documents_capital_website_finlogic_backend_deals_serializers_fund_py", "target": "serializers_fund_capitalcallserializer", "relation": "contains", "confidence": "EXTRACTED", "source_file": "C:\\Users\\poude\\Documents\\capital website\\finlogic\\backend\\deals\\serializers\\fund.py", "source_location": "L247", "weight": 1.0}, {"source": "c_users_poude_documents_capital_website_finlogic_backend_deals_serializers_fund_py", "target": "serializers_fund_meta", "relation": "contains", "confidence": "EXTRACTED", "source_file": "C:\\Users\\poude\\Documents\\capital website\\finlogic\\backend\\deals\\serializers\\fund.py", "source_location": "L258", "weight": 1.0}, {"source": "serializers_fund_capitalcallserializer", "target": "serializers_fund_capitalcallserializer_get_lp_profile_detail", "relation": "method", "confidence": "EXTRACTED", "source_file": "C:\\Users\\poude\\Documents\\capital website\\finlogic\\backend\\deals\\serializers\\fund.py", "source_location": "L271", "weight": 1.0}, {"source": "c_users_poude_documents_capital_website_finlogic_backend_deals_serializers_fund_py", "target": "serializers_fund_distributionserializer", "relation": "contains", "confidence": "EXTRACTED", "source_file": "C:\\Users\\poude\\Documents\\capital website\\finlogic\\backend\\deals\\serializers\\fund.py", "source_location": "L287", "weight": 1.0}, {"source": "c_users_poude_documents_capital_website_finlogic_backend_deals_serializers_fund_py", "target": "serializers_fund_meta", "relation": "contains", "confidence": "EXTRACTED", "source_file": "C:\\Users\\poude\\Documents\\capital website\\finlogic\\backend\\deals\\serializers\\fund.py", "source_location": "L293", "weight": 1.0}, {"source": "c_users_poude_documents_capital_website_finlogic_backend_deals_serializers_fund_py", "target": "serializers_fund_lpdashboardfundserializer", "relation": "contains", "confidence": "EXTRACTED", "source_file": "C:\\Users\\poude\\Documents\\capital website\\finlogic\\backend\\deals\\serializers\\fund.py", "source_location": "L309", "weight": 1.0}, {"source": "c_users_poude_documents_capital_website_finlogic_backend_deals_serializers_fund_py", "target": "serializers_fund_meta", "relation": "contains", "confidence": "EXTRACTED", "source_file": "C:\\Users\\poude\\Documents\\capital website\\finlogic\\backend\\deals\\serializers\\fund.py", "source_location": "L316", "weight": 1.0}, {"source": "serializers_fund_lpdashboardfundserializer", "target": "serializers_fund_lpdashboardfundserializer_get_my_commitment", "relation": "method", "confidence": "EXTRACTED", "source_file": "C:\\Users\\poude\\Documents\\capital website\\finlogic\\backend\\deals\\serializers\\fund.py", "source_location": "L326", "weight": 1.0}, {"source": "serializers_fund_lpdashboardfundserializer", "target": "serializers_fund_lpdashboardfundserializer_get_approved_deals_count", "relation": "method", "confidence": "EXTRACTED", "source_file": "C:\\Users\\poude\\Documents\\capital website\\finlogic\\backend\\deals\\serializers\\fund.py", "source_location": "L337", "weight": 1.0}, {"source": "serializers_fund_lpdashboardfundserializer", "target": "serializers_fund_lpdashboardfundserializer_get_total_documents_count", "relation": "method", "confidence": "EXTRACTED", "source_file": "C:\\Users\\poude\\Documents\\capital website\\finlogic\\backend\\deals\\serializers\\fund.py", "source_location": "L342", "weight": 1.0}, {"source": "serializers_fund_lpdashboardfundserializer", "target": "serializers_fund_lpdashboardfundserializer_get_pending_action_count", "relation": "method", "confidence": "EXTRACTED", "source_file": "C:\\Users\\poude\\Documents\\capital website\\finlogic\\backend\\deals\\serializers\\fund.py", "source_location": "L345", "weight": 1.0}, {"source": "c_users_poude_documents_capital_website_finlogic_backend_deals_serializers_fund_py", "target": "serializers_fund_managementfeeaccrualserializer", "relation": "contains", "confidence": "EXTRACTED", "source_file": "C:\\Users\\poude\\Documents\\capital website\\finlogic\\backend\\deals\\serializers\\fund.py", "source_location": "L363", "weight": 1.0}, {"source": "c_users_poude_documents_capital_website_finlogic_backend_deals_serializers_fund_py", "target": "serializers_fund_meta", "relation": "contains", "confidence": "EXTRACTED", "source_file": "C:\\Users\\poude\\Documents\\capital website\\finlogic\\backend\\deals\\serializers\\fund.py", "source_location": "L364", "weight": 1.0}, {"source": "c_users_poude_documents_capital_website_finlogic_backend_deals_serializers_fund_py", "target": "serializers_fund_gpinvestordashboardserializer", "relation": "contains", "confidence": "EXTRACTED", "source_file": "C:\\Users\\poude\\Documents\\capital website\\finlogic\\backend\\deals\\serializers\\fund.py", "source_location": "L374", "weight": 1.0}, {"source": "c_users_poude_documents_capital_website_finlogic_backend_deals_serializers_fund_py", "target": "serializers_fund_lpportfolioserializer", "relation": "contains", "confidence": "EXTRACTED", "source_file": "C:\\Users\\poude\\Documents\\capital website\\finlogic\\backend\\deals\\serializers\\fund.py", "source_location": "L388", "weight": 1.0}, {"source": "c_users_poude_documents_capital_website_finlogic_backend_deals_serializers_fund_py", "target": "serializers_fund_meta", "relation": "contains", "confidence": "EXTRACTED", "source_file": "C:\\Users\\poude\\Documents\\capital website\\finlogic\\backend\\deals\\serializers\\fund.py", "source_location": "L393", "weight": 1.0}, {"source": "serializers_fund_lpportfolioserializer", "target": "serializers_fund_lpportfolioserializer_get_anonymized_name", "relation": "method", "confidence": "EXTRACTED", "source_file": "C:\\Users\\poude\\Documents\\capital website\\finlogic\\backend\\deals\\serializers\\fund.py", "source_location": "L400", "weight": 1.0}, {"source": "c_users_poude_documents_capital_website_finlogic_backend_deals_serializers_fund_py", "target": "serializers_fund_lpsupportrequestserializer", "relation": "contains", "confidence": "EXTRACTED", "source_file": "C:\\Users\\poude\\Documents\\capital website\\finlogic\\backend\\deals\\serializers\\fund.py", "source_location": "L410", "weight": 1.0}, {"source": "c_users_poude_documents_capital_website_finlogic_backend_deals_serializers_fund_py", "target": "serializers_fund_meta", "relation": "contains", "confidence": "EXTRACTED", "source_file": "C:\\Users\\poude\\Documents\\capital website\\finlogic\\backend\\deals\\serializers\\fund.py", "source_location": "L414", "weight": 1.0}, {"source": "serializers_fund_lpdashboardfundserializer_get_my_commitment", "target": "serializers_fund_lpfundcommitmentserializer", "relation": "calls", "confidence": "EXTRACTED", "source_file": "C:\\Users\\poude\\Documents\\capital website\\finlogic\\backend\\deals\\serializers\\fund.py", "source_location": "L333", "weight": 1.0}, {"source": "serializers_fund_rationale_1", "target": "c_users_poude_documents_capital_website_finlogic_backend_deals_serializers_fund_py", "relation": "rationale_for", "confidence": "EXTRACTED", "source_file": "C:\\Users\\poude\\Documents\\capital website\\finlogic\\backend\\deals\\serializers\\fund.py", "source_location": "L1", "weight": 1.0}, {"source": "serializers_fund_rationale_310", "target": "serializers_fund_lpdashboardfundserializer", "relation": "rationale_for", "confidence": "EXTRACTED", "source_file": "C:\\Users\\poude\\Documents\\capital website\\finlogic\\backend\\deals\\serializers\\fund.py", "source_location": "L310", "weight": 1.0}, {"source": "serializers_fund_rationale_375", "target": "serializers_fund_gpinvestordashboardserializer", "relation": "rationale_for", "confidence": "EXTRACTED", "source_file": "C:\\Users\\poude\\Documents\\capital website\\finlogic\\backend\\deals\\serializers\\fund.py", "source_location": "L375", "weight": 1.0}, {"source": "serializers_fund_rationale_389", "target": "serializers_fund_lpportfolioserializer", "relation": "rationale_for", "confidence": "EXTRACTED", "source_file": "C:\\Users\\poude\\Documents\\capital website\\finlogic\\backend\\deals\\serializers\\fund.py", "source_location": "L389", "weight": 1.0}], "raw_calls": [{"caller_nid": "serializers_fund_fundserializer_get_performance", "callee": "_calculate_fund_performance_metrics", "is_member_call": false, "source_file": "C:\\Users\\poude\\Documents\\capital website\\finlogic\\backend\\deals\\serializers\\fund.py", "source_location": "L118"}, {"caller_nid": "serializers_fund_capitalcallserializer_get_lp_profile_detail", "callee": "str", "is_member_call": false, "source_file": "C:\\Users\\poude\\Documents\\capital website\\finlogic\\backend\\deals\\serializers\\fund.py", "source_location": "L275"}, {"caller_nid": "serializers_fund_lpdashboardfundserializer_get_my_commitment", "callee": "get", "is_member_call": true, "source_file": "C:\\Users\\poude\\Documents\\capital website\\finlogic\\backend\\deals\\serializers\\fund.py", "source_location": "L327"}, {"caller_nid": "serializers_fund_lpdashboardfundserializer_get_my_commitment", "callee": "get", "is_member_call": true, "source_file": "C:\\Users\\poude\\Documents\\capital website\\finlogic\\backend\\deals\\serializers\\fund.py", "source_location": "L332"}, {"caller_nid": "serializers_fund_lpdashboardfundserializer_get_approved_deals_count", "callee": "count", "is_member_call": true, "source_file": "C:\\Users\\poude\\Documents\\capital website\\finlogic\\backend\\deals\\serializers\\fund.py", "source_location": "L338"}, {"caller_nid": "serializers_fund_lpdashboardfundserializer_get_approved_deals_count", "callee": "filter", "is_member_call": true, "source_file": "C:\\Users\\poude\\Documents\\capital website\\finlogic\\backend\\deals\\serializers\\fund.py", "source_location": "L338"}, {"caller_nid": "serializers_fund_lpdashboardfundserializer_get_total_documents_count", "callee": "count", "is_member_call": true, "source_file": "C:\\Users\\poude\\Documents\\capital website\\finlogic\\backend\\deals\\serializers\\fund.py", "source_location": "L343"}, {"caller_nid": "serializers_fund_lpdashboardfundserializer_get_total_documents_count", "callee": "filter", "is_member_call": true, "source_file": "C:\\Users\\poude\\Documents\\capital website\\finlogic\\backend\\deals\\serializers\\fund.py", "source_location": "L343"}, {"caller_nid": "serializers_fund_lpdashboardfundserializer_get_pending_action_count", "callee": "get", "is_member_call": true, "source_file": "C:\\Users\\poude\\Documents\\capital website\\finlogic\\backend\\deals\\serializers\\fund.py", "source_location": "L346"}, {"caller_nid": "serializers_fund_lpdashboardfundserializer_get_pending_action_count", "callee": "hasattr", "is_member_call": false, "source_file": "C:\\Users\\poude\\Documents\\capital website\\finlogic\\backend\\deals\\serializers\\fund.py", "source_location": "L347"}, {"caller_nid": "serializers_fund_lpdashboardfundserializer_get_pending_action_count", "callee": "filter", "is_member_call": true, "source_file": "C:\\Users\\poude\\Documents\\capital website\\finlogic\\backend\\deals\\serializers\\fund.py", "source_location": "L352"}, {"caller_nid": "serializers_fund_lpdashboardfundserializer_get_pending_action_count", "callee": "values_list", "is_member_call": true, "source_file": "C:\\Users\\poude\\Documents\\capital website\\finlogic\\backend\\deals\\serializers\\fund.py", "source_location": "L354"}, {"caller_nid": "serializers_fund_lpdashboardfundserializer_get_pending_action_count", "callee": "filter", "is_member_call": true, "source_file": "C:\\Users\\poude\\Documents\\capital website\\finlogic\\backend\\deals\\serializers\\fund.py", "source_location": "L354"}, {"caller_nid": "serializers_fund_lpdashboardfundserializer_get_pending_action_count", "callee": "count", "is_member_call": true, "source_file": "C:\\Users\\poude\\Documents\\capital website\\finlogic\\backend\\deals\\serializers\\fund.py", "source_location": "L360"}, {"caller_nid": "serializers_fund_lpdashboardfundserializer_get_pending_action_count", "callee": "exclude", "is_member_call": true, "source_file": "C:\\Users\\poude\\Documents\\capital website\\finlogic\\backend\\deals\\serializers\\fund.py", "source_location": "L360"}, {"caller_nid": "serializers_fund_lpportfolioserializer_get_anonymized_name", "callee": "get_sector_display", "is_member_call": true, "source_file": "C:\\Users\\poude\\Documents\\capital website\\finlogic\\backend\\deals\\serializers\\fund.py", "source_location": "L402"}, {"caller_nid": "serializers_fund_lpportfolioserializer_get_anonymized_name", "callee": "upper", "is_member_call": true, "source_file": "C:\\Users\\poude\\Documents\\capital website\\finlogic\\backend\\deals\\serializers\\fund.py", "source_location": "L402"}, {"caller_nid": "serializers_fund_lpportfolioserializer_get_anonymized_name", "callee": "str", "is_member_call": false, "source_file": "C:\\Users\\poude\\Documents\\capital website\\finlogic\\backend\\deals\\serializers\\fund.py", "source_location": "L402"}]}