{"nodes": [{"id": "c_users_poude_documents_capital_website_finlogic_frontend_src_components_insights_coursecard_js", "label": "CourseCard.js", "file_type": "code", "source_file": "C:\\Users\\poude\\Documents\\capital website\\finlogic\\frontend\\src\\components\\insights\\CourseCard.js", "source_location": "L1"}, {"id": "insights_coursecard_coursecard", "label": "CourseCard()", "file_type": "code", "source_file": "C:\\Users\\poude\\Documents\\capital website\\finlogic\\frontend\\src\\components\\insights\\CourseCard.js", "source_location": "L4"}], "edges": [{"source": "c_users_poude_documents_capital_website_finlogic_frontend_src_components_insights_coursecard_js", "target": "link", "relation": "imports_from", "confidence": "EXTRACTED", "source_file": "C:\\Users\\poude\\Documents\\capital website\\finlogic\\frontend\\src\\components\\insights\\CourseCard.js", "source_location": "L1", "weight": 1.0}, {"source": "c_users_poude_documents_capital_website_finlogic_frontend_src_components_insights_coursecard_js", "target": "lucide_react", "relation": "imports_from", "confidence": "EXTRACTED", "source_file": "C:\\Users\\poude\\Documents\\capital website\\finlogic\\frontend\\src\\components\\insights\\CourseCard.js", "source_location": "L2", "weight": 1.0}, {"source": "c_users_poude_documents_capital_website_finlogic_frontend_src_components_insights_coursecard_js", "target": "insights_coursecard_coursecard", "relation": "contains", "confidence": "EXTRACTED", "source_file": "C:\\Users\\poude\\Documents\\capital website\\finlogic\\frontend\\src\\components\\insights\\CourseCard.js", "source_location": "L4", "weight": 1.0}], "raw_calls": []}