{"nodes": [{"id": "c_users_poude_documents_capital_website_finlogic_backend_idea_validator_admin_py", "label": "admin.py", "file_type": "code", "source_file": "C:\\Users\\poude\\Documents\\capital website\\finlogic\\backend\\idea_validator\\admin.py", "source_location": "L1"}, {"id": "idea_validator_admin_optioninline", "label": "OptionInline", "file_type": "code", "source_file": "C:\\Users\\poude\\Documents\\capital website\\finlogic\\backend\\idea_validator\\admin.py", "source_location": "L12"}, {"id": "idea_validator_admin_questionadmin", "label": "QuestionAdmin", "file_type": "code", "source_file": "C:\\Users\\poude\\Documents\\capital website\\finlogic\\backend\\idea_validator\\admin.py", "source_location": "L17"}, {"id": "idea_validator_admin_ideavalidationsessionadmin", "label": "IdeaValidationSessionAdmin", "file_type": "code", "source_file": "C:\\Users\\poude\\Documents\\capital website\\finlogic\\backend\\idea_validator\\admin.py", "source_location": "L25"}, {"id": "idea_validator_admin_validationansweradmin", "label": "ValidationAnswerAdmin", "file_type": "code", "source_file": "C:\\Users\\poude\\Documents\\capital website\\finlogic\\backend\\idea_validator\\admin.py", "source_location": "L32"}, {"id": "idea_validator_admin_ideavalidatorquotaadmin", "label": "IdeaValidatorQuotaAdmin", "file_type": "code", "source_file": "C:\\Users\\poude\\Documents\\capital website\\finlogic\\backend\\idea_validator\\admin.py", "source_location": "L37"}, {"id": "idea_validator_admin_ideavalidatorquotaadmin_save_model", "label": ".save_model()", "file_type": "code", "source_file": "C:\\Users\\poude\\Documents\\capital website\\finlogic\\backend\\idea_validator\\admin.py", "source_location": "L42"}, {"id": "idea_validator_admin_quotaadjustmentlogadmin", "label": "QuotaAdjustmentLogAdmin", "file_type": "code", "source_file": "C:\\Users\\poude\\Documents\\capital website\\finlogic\\backend\\idea_validator\\admin.py", "source_location": "L61"}, {"id": "idea_validator_admin_validatorpromptadmin", "label": "ValidatorPromptAdmin", "file_type": "code", "source_file": "C:\\Users\\poude\\Documents\\capital website\\finlogic\\backend\\idea_validator\\admin.py", "source_location": "L68"}], "edges": [{"source": "c_users_poude_documents_capital_website_finlogic_backend_idea_validator_admin_py", "target": "django_contrib", "relation": "imports_from", "confidence": "EXTRACTED", "source_file": "C:\\Users\\poude\\Documents\\capital website\\finlogic\\backend\\idea_validator\\admin.py", "source_location": "L1", "weight": 1.0}, {"source": "c_users_poude_documents_capital_website_finlogic_backend_idea_validator_admin_py", "target": "c_users_poude_documents_capital_website_finlogic_backend_idea_validator_models_py", "relation": "imports_from", "confidence": "EXTRACTED", "source_file": "C:\\Users\\poude\\Documents\\capital website\\finlogic\\backend\\idea_validator\\admin.py", "source_location": "L2", "weight": 1.0}, {"source": "c_users_poude_documents_capital_website_finlogic_backend_idea_validator_admin_py", "target": "idea_validator_admin_optioninline", "relation": "contains", "confidence": "EXTRACTED", "source_file": "C:\\Users\\poude\\Documents\\capital website\\finlogic\\backend\\idea_validator\\admin.py", "source_location": "L12", "weight": 1.0}, {"source": "c_users_poude_documents_capital_website_finlogic_backend_idea_validator_admin_py", "target": "idea_validator_admin_questionadmin", "relation": "contains", "confidence": "EXTRACTED", "source_file": "C:\\Users\\poude\\Documents\\capital website\\finlogic\\backend\\idea_validator\\admin.py", "source_location": "L17", "weight": 1.0}, {"source": "c_users_poude_documents_capital_website_finlogic_backend_idea_validator_admin_py", "target": "idea_validator_admin_ideavalidationsessionadmin", "relation": "contains", "confidence": "EXTRACTED", "source_file": "C:\\Users\\poude\\Documents\\capital website\\finlogic\\backend\\idea_validator\\admin.py", "source_location": "L25", "weight": 1.0}, {"source": "c_users_poude_documents_capital_website_finlogic_backend_idea_validator_admin_py", "target": "idea_validator_admin_validationansweradmin", "relation": "contains", "confidence": "EXTRACTED", "source_file": "C:\\Users\\poude\\Documents\\capital website\\finlogic\\backend\\idea_validator\\admin.py", "source_location": "L32", "weight": 1.0}, {"source": "c_users_poude_documents_capital_website_finlogic_backend_idea_validator_admin_py", "target": "idea_validator_admin_ideavalidatorquotaadmin", "relation": "contains", "confidence": "EXTRACTED", "source_file": "C:\\Users\\poude\\Documents\\capital website\\finlogic\\backend\\idea_validator\\admin.py", "source_location": "L37", "weight": 1.0}, {"source": "idea_validator_admin_ideavalidatorquotaadmin", "target": "idea_validator_admin_ideavalidatorquotaadmin_save_model", "relation": "method", "confidence": "EXTRACTED", "source_file": "C:\\Users\\poude\\Documents\\capital website\\finlogic\\backend\\idea_validator\\admin.py", "source_location": "L42", "weight": 1.0}, {"source": "c_users_poude_documents_capital_website_finlogic_backend_idea_validator_admin_py", "target": "idea_validator_admin_quotaadjustmentlogadmin", "relation": "contains", "confidence": "EXTRACTED", "source_file": "C:\\Users\\poude\\Documents\\capital website\\finlogic\\backend\\idea_validator\\admin.py", "source_location": "L61", "weight": 1.0}, {"source": "c_users_poude_documents_capital_website_finlogic_backend_idea_validator_admin_py", "target": "idea_validator_admin_validatorpromptadmin", "relation": "contains", "confidence": "EXTRACTED", "source_file": "C:\\Users\\poude\\Documents\\capital website\\finlogic\\backend\\idea_validator\\admin.py", "source_location": "L68", "weight": 1.0}], "raw_calls": [{"caller_nid": "idea_validator_admin_ideavalidatorquotaadmin_save_model", "callee": "get", "is_member_call": true, "source_file": "C:\\Users\\poude\\Documents\\capital website\\finlogic\\backend\\idea_validator\\admin.py", "source_location": "L45"}, {"caller_nid": "idea_validator_admin_ideavalidatorquotaadmin_save_model", "callee": "create", "is_member_call": true, "source_file": "C:\\Users\\poude\\Documents\\capital website\\finlogic\\backend\\idea_validator\\admin.py", "source_location": "L50"}, {"caller_nid": "idea_validator_admin_ideavalidatorquotaadmin_save_model", "callee": "super", "is_member_call": false, "source_file": "C:\\Users\\poude\\Documents\\capital website\\finlogic\\backend\\idea_validator\\admin.py", "source_location": "L58"}]}